grizabella/__init__.py
grizabella/api/__init__.py
grizabella/api/client.py
grizabella/cli/__init__.py
grizabella/config/__init__.py
grizabella/core/__init__.py
grizabella/core/_db_manager_helpers.py
grizabella/core/connection_pool.py
grizabella/core/db_manager.py
grizabella/core/db_manager_factory.py
grizabella/core/db_paths.py
grizabella/core/exceptions.py
grizabella/core/models.py
grizabella/core/query_engine.py
grizabella/core/query_models.py
grizabella/core/resource_monitor.py
grizabella/core/resource_monitor_dashboard.py
grizabella/core/utils.py
grizabella/db_layers/__init__.py
grizabella/db_layers/common/__init__.py
grizabella/db_layers/common/base_adapter.py
grizabella/db_layers/kuzu/__init__.py
grizabella/db_layers/kuzu/kuzu_adapter.py
grizabella/db_layers/kuzu/thread_safe_kuzu_adapter.py
grizabella/db_layers/lancedb/__init__.py
grizabella/db_layers/lancedb/lancedb_adapter.py
grizabella/db_layers/sqlite/__init__.py
grizabella/db_layers/sqlite/sqlite_adapter.py
grizabella/db_layers/sqlite/thread_safe_sqlite_adapter.py
grizabella/mcp/__init__.py
grizabella/mcp/enhanced_server.py
grizabella/mcp/server.py
grizabella/ui/__init__.py
grizabella/ui/app.py
grizabella/ui/delegates/__init__.py
grizabella/ui/dialogs/__init__.py
grizabella/ui/dialogs/embedding_definition_dialog.py
grizabella/ui/dialogs/object_instance_dialog.py
grizabella/ui/dialogs/object_type_dialog.py
grizabella/ui/dialogs/relation_instance_dialog.py
grizabella/ui/dialogs/relation_type_dialog.py
grizabella/ui/main_window.py
grizabella/ui/models/__init__.py
grizabella/ui/models/object_instance_table_model.py
grizabella/ui/models/relation_instance_table_model.py
grizabella/ui/resources/__init__.py
grizabella/ui/resources/icons/__init__.py
grizabella/ui/resources/styles/__init__.py
grizabella/ui/threads/__init__.py
grizabella/ui/threads/api_client_thread.py
grizabella/ui/views/__init__.py
grizabella/ui/views/connection_view.py
grizabella/ui/views/embedding_definition_view.py
grizabella-0.6.1.dist-info/LICENSE
grizabella-0.6.1.dist-info/METADATA
grizabella-0.6.1.dist-info/WHEEL
grizabella-0.6.1.dist-info/entry_points.txt
grizabella-0.6.1.dist-info/RECORD
