Metadata-Version: 2.3
Name: grizabella
Version: 0.6.1
Summary: A tri-layer memory framework for LLM solutions.
License: MIT
Keywords: python,llm,memory,vector-database,graph-database,sqlite,lancedb,real_ladybug,pyside6,sentence-transformers,fastmcp,ai,multi-modal
Author: Grizabella Project Contributors
Author-email: contributors@example.com
Requires-Python: >=3.12,<3.14
Classifier: Development Status :: 4 - Beta
Classifier: Intended Audience :: Developers
Classifier: License :: OSI Approved :: MIT License
Classifier: Operating System :: OS Independent
Classifier: Programming Language :: Python :: 3
Classifier: Programming Language :: Python :: 3.12
Classifier: Programming Language :: Python :: 3.13
Classifier: Programming Language :: Python :: 3.11
Classifier: Topic :: Database
Classifier: Topic :: Scientific/Engineering :: Artificial Intelligence
Classifier: Topic :: Software Development :: Libraries :: Python Modules
Requires-Dist: PySide6 (>=6.7.0,<7.0.0)
Requires-Dist: fastmcp (>=2.10.6,<3.0.0)
Requires-Dist: kuzu (==0.10.1)
Requires-Dist: lancedb (>=0.24.0,<0.25.0)
Requires-Dist: litellm (>=1.74.4,<2.0.0)
Requires-Dist: optimum (>=1.26.1,<2.0.0)
Requires-Dist: pandas (>=2.3.0,<3.0.0)
Requires-Dist: psutil (>=7.0.0,<8.0.0)
Requires-Dist: pydantic (>=2.11.5,<3.0.0)
Requires-Dist: pytest-asyncio (>=1.1.0,<2.0.0)
Requires-Dist: qt_material (>=2.14,<3.0)
Requires-Dist: real_ladybug (>=0.12.2,<0.13.0)
Requires-Dist: sentence-transformers (>=3.0.0,<4.0.0)
Project-URL: Documentation, https://pwilkin.github.io/grizabella
Project-URL: Homepage, https://github.com/pwilkin/grizabella
Project-URL: Repository, https://github.com/pwilkin/grizabella
